{"Adult": 0, "Arts & Entertainment": {"Celebrities & Entertainment News": 1, "Comics & Animation": 2, "Entertainment Industry": 3, "Events & Listings": 4, "Fun & Trivia": 5, "Humor": 6, "Movies": 7, "Music & Audio": 8, "Offbeat": 9, "Online Media": 10, "Performing Arts": 11, "TV & Video": 12, "Visual Art & Design": 13}, "Autos & Vehicles": {"Bicycles & Accessories": 14, "Boats & Watercraft": 15, "Campers & RVs": 16, "Classic Vehicles": 17, "Commercial Vehicles": 18, "Motor Vehicles (By Type)": 19, "Vehicle Codes & Driving Laws": 20, "Vehicle Parts & Services": 21, "Vehicle Shopping": 22, "Vehicle Shows": 23}, "Beauty & Fitness": {"Beauty Pageants": 24, "Body Art": 25, "Cosmetic Procedures": 26, "Cosmetology & Beauty Professionals": 27, "Face & Body Care": 28, "Fashion & Style": 29, "Fitness": 30, "Hair Care": 31, "Spas & Beauty Services": 32, "Weight Loss": 33}, "Books & Literature": {"Children's Literature": 34, "E-Books": 35, "Fan Fiction": 36, "Literary Classics": 37, "Poetry": 38, "Writers Resources": 39}, "Business & Industrial": {"Advertising & Marketing": 40, "Aerospace & Defense": 41, "Agriculture & Forestry": 42, "Automotive Industry": 43, "Business Education": 44, "Business Finance": 45, "Business Operations": 46, "Business Services": 47, "Chemicals Industry": 48, "Construction & Maintenance": 49, "Energy & Utilities": 50, "Hospitality Industry": 51, "Industrial Materials & Equipment": 52, "Manufacturing": 53, "Metals & Mining": 54, "Pharmaceuticals & Biotech": 55, "Printing & Publishing": 56, "Retail Trade": 57, "Small Business": 58, "Textiles & Nonwovens": 59, "Transportation & Logistics": 60}, "Computers & Electronics": {"CAD & CAM": 61, "Computer Hardware": 62, "Computer Security": 63, "Consumer Electronics": 64, "Electronics & Electrical": 65, "Enterprise Technology": 66, "Networking": 67, "Programming": 68, "Software": 69}, "Finance": {"Accounting & Auditing": 70, "Banking": 71, "Credit & Lending": 72, "Financial Planning & Management": 73, "Grants, Scholarships & Financial Aid": 74, "Insurance": 75, "Investing": 76}, "Food & Drink": {"Beverages": 77, "Cooking & Recipes": 78, "Food": 79, "Food & Grocery Retailers": 80, "Restaurants": 81}, "Games": {"Arcade & Coin-Op Games": 82, "Board Games": 83, "Card Games": 84, "Computer & Video Games": 85, "Family-Oriented Games & Activities": 86, "Gambling": 87, "Online Games": 88, "Puzzles & Brainteasers": 89, "Roleplaying Games": 90, "Table Games": 91, "Word Games": 92}, "Health": {"Aging & Geriatrics": 93, "Health Conditions": 94, "Health Education & Medical Training": 95, "Health Foundations & Medical Research": 96, "Medical Devices & Equipment": 97, "Medical Facilities & Services": 98, "Men's Health": 99, "Mental Health": 100, "Nursing": 101, "Nutrition": 102, "Oral & Dental Care": 103, "Pharmacy": 104, "Public Health": 105, "Reproductive Health": 106, "Substance Abuse": 107, "Vision Care": 108, "Women's Health": 109}, "Hobbies & Leisure": {"Clubs & Organizations": 110, "Crafts": 111, "Merit Prizes & Contests": 112, "Outdoors": 113, "Paintball": 114, "Radio Control & Modeling": 115, "Special Occasions": 116, "Water Activities": 117}, "Home & Garden": {"Bed & Bath": 118, "Domestic Services": 119, "Gardening & Landscaping": 120, "Home & Interior Decor": 121, "Home Appliances": 122, "Home Furnishings": 123, "Home Improvement": 124, "Home Safety & Security": 125, "Home Storage & Shelving": 126, "Home Swimming Pools, Saunas & Spas": 127, "HVAC & Climate Control": 128, "Kitchen & Dining": 129, "Laundry": 130, "Nursery & Playroom": 131, "Pest Control": 132, "Yard & Patio": 133}, "Internet & Telecom": {"Communications Equipment": 134, "Email & Messaging": 135, "Mobile & Wireless": 136, "Service Providers": 137, "Web Services": 138}, "Jobs & Education": {"Education": 139, "Jobs": 140}, "Law & Government": {"Government": 141, "Legal": 142, "Military": 143, "Public Safety": 144, "Social Services": 145}, "News": {"Business News": 146, "Gossip & Tabloid News": 147, "Health News": 148, "Politics": 149, "Sports News": 150, "Weather": 151}, "Online Communities": {"Blogging Resources & Services": 152, "Dating & Personals": 153, "File Sharing & Hosting": 154, "Online Goodies": 155, "Photo & Video Sharing": 156, "Social Networks": 157, "Virtual Worlds": 158}, "People & Society": {"Family & Relationships": 159, "Kids & Teens": 160, "Religion & Belief": 161, "Seniors & Retirement": 162, "Social Issues & Advocacy": 163, "Social Sciences": 164, "Subcultures & Niche Interests": 165}, "Pets & Animals": {"Animal Products & Services": 166, "Pets": 167, "Wildlife": 168}, "Real Estate": {"Real Estate Listings": 169, "Real Estate Services": 170}, "Reference": {"Directories & Listings": 171, "General Reference": 172, "Geographic Reference": 173, "Humanities": 174, "Language Resources": 175, "Libraries & Museums": 176}, "Science": {"Astronomy": 177, "Biological Sciences": 178, "Chemistry": 179, "Computer Science": 180, "Earth Sciences": 181, "Ecology & Environment": 182, "Engineering & Technology": 183, "Mathematics": 184, "Physics": 185, "Scientific Institutions": 186}, "Sensitive Subjects": 187, "Shopping": {"Antiques & Collectibles": 188, "Apparel": 189, "Auctions": 190, "Classifieds": 191, "Consumer Resources": 192, "Entertainment Media": 193, "Gifts & Special Event Items": 194, "Luxury Goods": 195, "Mass Merchants & Department Stores": 196, "Photo & Video Services": 197, "Tobacco Products": 198, "Toys": 199}, "Sports": {"Animal Sports": 200, "College Sports": 201, "Combat Sports": 202, "Extreme Sports": 203, "Fantasy Sports": 204, "Individual Sports": 205, "International Sports Competitions": 206, "Motor Sports": 207, "Sporting Goods": 208, "Sports Coaching & Training": 209, "Team Sports": 210, "Water Sports": 211, "Winter Sports": 212}, "Travel": {"Air Travel": 213, "Bus & Rail": 214, "Car Rental & Taxi Services": 215, "Cruises & Charters": 216, "Hotels & Accommodations": 217, "Specialty Travel": 218, "Tourist Destinations": 219}}